entities/BilanPartie.py
entities/Classement.py
entities/CoupInvalideDroite.py
entities/CoupInvalideGauche.py
entities/CoupInvalideSimultane.py
entities/Partie.py
entities/ResultatSimulation.py
entities/Strategie.py
entities/__init__.py
trollsAndCastles/__init__.py
trollsAndCastles/core.py
trollsAndCastles/exportToJSON.py
trollsAndCastles/gui.py
trollsAndCastles/rankings.py
trollsAndCastles/strategies.py
trollsAndCastles/entities/BilanPartie.py
trollsAndCastles/entities/Classement.py
trollsAndCastles/entities/CoupInvalideDroite.py
trollsAndCastles/entities/CoupInvalideGauche.py
trollsAndCastles/entities/CoupInvalideSimultane.py
trollsAndCastles/entities/Partie.py
trollsAndCastles/entities/ResultatSimulation.py
trollsAndCastles/entities/Strategie.py
trollsAndCastles/entities/__init__.py
trolls_and_castles-0.0.5.dist-info/LICENSE
trolls_and_castles-0.0.5.dist-info/METADATA
trolls_and_castles-0.0.5.dist-info/WHEEL
trolls_and_castles-0.0.5.dist-info/top_level.txt
trolls_and_castles-0.0.5.dist-info/RECORD
