Metadata-Version: 2.1
Name: trolls-and-castles
Version: 0.0.5
Summary: Trolls and Castles
Home-page: https://github.com/AndreLovichi/trollsAndCastles
Author: Romain André-Lovichi
Author-email: romain.andrelovichi@gmail.com
License: UNKNOWN
Project-URL: Bug Tracker, https://github.com/AndreLovichi/trollsAndCastles/issues
Platform: UNKNOWN
Classifier: Programming Language :: Python :: 3
Classifier: License :: OSI Approved :: MIT License
Classifier: Operating System :: OS Independent
Requires-Python: >=3.6
License-File: LICENSE
